speccify/__init__.py
speccify/decorator.py
speccify/generator.py
speccify/py.typed
speccify/typing.py
speccify-0.2.0.dist-info/LICENSE
speccify-0.2.0.dist-info/WHEEL
speccify-0.2.0.dist-info/METADATA
speccify-0.2.0.dist-info/RECORD
